{"stats":{"minecraft:dropped":{"minecraft:iron_sword":2,"minecraft:birch_planks":15,"minecraft:cooked_beef":14,"minecraft:oak_log":1,"minecraft:cyan_glazed_terracotta":1,"minecraft:purple_glazed_terracotta":1,"minecraft:cooked_porkchop":5,"minecraft:leather":4,"minecraft:saddle":3,"minecraft:rail":40,"minecraft:leather_helmet":2,"minecraft:cod":1,"minecraft:orange_glazed_terracotta":1,"minecraft:dirt":26,"minecraft:dark_oak_log":41,"minecraft:sand":2,"minecraft:acacia_door":1,"minecraft:dark_oak_planks":64,"minecraft:pink_glazed_terracotta":1,"minecraft:white_wool":8,"minecraft:bone":1,"minecraft:red_glazed_terracotta":1,"minecraft:dark_oak_door":9,"minecraft:stone_axe":2,"minecraft:sugar_cane":1,"minecraft:wheat":1,"minecraft:birch_sapling":9,"minecraft:beetroot":1,"minecraft:black_terracotta":1,"minecraft:rotten_flesh":38,"minecraft:cooked_mutton":2,"minecraft:golden_shovel":68,"minecraft:infested_stone_bricks":2,"minecraft:carrot":8,"minecraft:black_glazed_terracotta":1,"minecraft:tipped_arrow":57,"minecraft:acacia_sapling":1,"minecraft:chest":2,"minecraft:ladder":2,"minecraft:powered_rail":3,"minecraft:acacia_fence":1,"minecraft:written_book":1,"minecraft:white_glazed_terracotta":1,"minecraft:water_bucket":1,"minecraft:stone_hoe":4,"minecraft:wheat_seeds":1,"minecraft:minecart":4,"minecraft:poisonous_potato":5,"minecraft:cobblestone":19,"minecraft:yellow_terracotta":3,"minecraft:oak_fence":6,"minecraft:feather":3,"minecraft:lead":9,"minecraft:light_gray_glazed_terracotta":1,"minecraft:sign":3,"minecraft:lava_bucket":25,"minecraft:diorite":2,"minecraft:torch":2,"minecraft:yellow_glazed_terracotta":1,"minecraft:brown_terracotta":1,"minecraft:iron_leggings":1,"minecraft:green_glazed_terracotta":1,"minecraft:blue_glazed_terracotta":1,"minecraft:magenta_glazed_terracotta":1,"minecraft:iron_axe":2,"minecraft:string":2,"minecraft:bucket":13,"minecraft:acacia_planks":44,"minecraft:redstone":1,"minecraft:light_blue_glazed_terracotta":1,"minecraft:gray_glazed_terracotta":1,"minecraft:stone_shovel":6,"minecraft:brown_glazed_terracotta":1,"minecraft:light_gray_wool":5,"minecraft:iron_boots":1,"minecraft:spruce_fence":1,"minecraft:glass_pane":1,"minecraft:pumpkin_seeds":1,"minecraft:red_terracotta":1,"minecraft:filled_map":1,"minecraft:diamond_sword":3,"minecraft:stone":2,"minecraft:lime_glazed_terracotta":1,"minecraft:iron_chestplate":1,"minecraft:andesite":5,"minecraft:oak_sapling":2,"minecraft:golden_sword":1,"minecraft:brown_bed":1,"minecraft:stripped_acacia_log":1,"minecraft:bow":2,"minecraft:stone_pickaxe":4,"minecraft:wooden_pickaxe":1,"minecraft:terracotta":2},"minecraft:custom":{"minecraft:animals_bred":83,"minecraft:interact_with_crafting_table":193,"minecraft:leave_game":26,"minecraft:time_since_death":500938,"minecraft:sprint_one_cm":1949547,"minecraft:damage_blocked_by_shield":880,"minecraft:drop":309,"minecraft:talked_to_villager":1,"minecraft:deaths":4,"minecraft:jump":7037,"minecraft:interact_with_brewingstand":1,"minecraft:walk_on_water_one_cm":426354,"minecraft:interact_with_furnace":192,"minecraft:play_one_minute":1521812,"minecraft:sleep_in_bed":46,"minecraft:damage_dealt":23459,"minecraft:crouch_one_cm":121729,"minecraft:horse_one_cm":1961794,"minecraft:mob_kills":190,"minecraft:climb_one_cm":35633,"minecraft:walk_one_cm":6502703,"minecraft:sneak_time":36195,"minecraft:walk_under_water_one_cm":124156,"minecraft:boat_one_cm":204201,"minecraft:tune_noteblock":4,"minecraft:time_since_rest":16638,"minecraft:damage_taken":4484,"minecraft:minecart_one_cm":340806,"minecraft:swim_one_cm":104806,"minecraft:fly_one_cm":4470509,"minecraft:open_chest":818,"minecraft:fall_one_cm":84953},"minecraft:broken":{"minecraft:golden_helmet":1,"minecraft:stone_pickaxe":18,"minecraft:stone_axe":8,"minecraft:wooden_axe":1,"minecraft:stone_shovel":1,"minecraft:stone_sword":1,"minecraft:iron_pickaxe":1},"minecraft:mined":{"minecraft:dark_oak_planks":334,"minecraft:white_bed":5,"minecraft:jungle_leaves":13,"minecraft:brewing_stand":1,"minecraft:granite":3,"minecraft:red_sand":100,"minecraft:acacia_log":212,"minecraft:grass_block":248,"minecraft:jungle_log":32,"minecraft:nether_wart":30,"minecraft:spawner":1,"minecraft:dark_oak_trapdoor":2,"minecraft:iron_ore":64,"minecraft:pumpkin":6,"minecraft:brown_bed":1,"minecraft:dark_oak_stairs":12,"minecraft:brown_glazed_terracotta":1,"minecraft:oak_stairs":10,"minecraft:tripwire":1,"minecraft:cut_sandstone":1,"minecraft:kelp_plant":48,"minecraft:orange_terracotta":667,"minecraft:clay":1,"minecraft:torch":86,"minecraft:light_gray_terracotta":35,"minecraft:poppy":20,"minecraft:chest":11,"minecraft:dead_bush":21,"minecraft:nether_quartz_ore":19,"minecraft:glass":1,"minecraft:cobblestone":153,"minecraft:oak_planks":21,"minecraft:wall_torch":45,"minecraft:seagrass":1,"minecraft:white_terracotta":20,"minecraft:powered_rail":33,"minecraft:dark_oak_slab":14,"minecraft:sign":6,"minecraft:birch_log":14,"minecraft:wheat":142,"minecraft:pumpkin_stem":5,"minecraft:grass":59,"minecraft:oak_log":154,"minecraft:beetroots":79,"minecraft:dark_oak_sapling":10,"minecraft:acacia_fence":32,"minecraft:sand":65,"minecraft:dirt":272,"minecraft:netherrack":54,"minecraft:oak_leaves":22,"minecraft:yellow_terracotta":429,"minecraft:wall_sign":2,"minecraft:dark_oak_leaves":32,"minecraft:dark_oak_log":204,"minecraft:dark_oak_fence":18,"minecraft:lever":1,"minecraft:stone_button":6,"minecraft:kelp":3,"minecraft:sandstone":10,"minecraft:redstone_ore":9,"minecraft:oak_trapdoor":1,"minecraft:furnace":5,"minecraft:carrots":84,"minecraft:andesite":1,"minecraft:acacia_stairs":6,"minecraft:dark_oak_fence_gate":4,"minecraft:detector_rail":4,"minecraft:bookshelf":3,"minecraft:potatoes":14,"minecraft:rail":86,"minecraft:stone":301,"minecraft:redstone_wall_torch":8,"minecraft:oak_slab":1,"minecraft:acacia_leaves":224,"minecraft:dandelion":1,"minecraft:oak_fence":130,"minecraft:crafting_table":12,"minecraft:lapis_ore":13,"minecraft:diorite":3,"minecraft:red_terracotta":16,"minecraft:coarse_dirt":2,"minecraft:cobblestone_wall":4,"minecraft:acacia_fence_gate":3,"minecraft:redstone_torch":13,"minecraft:grass_path":1,"minecraft:coal_ore":172,"minecraft:brown_terracotta":217,"minecraft:terracotta":1029,"minecraft:acacia_planks":52,"minecraft:gold_ore":53},"minecraft:killed":{"minecraft:spider":20,"minecraft:cod":1,"minecraft:skeleton":9,"minecraft:chicken":36,"minecraft:magma_cube":6,"minecraft:pig":29,"minecraft:creeper":4,"minecraft:sheep":15,"minecraft:zombie":26,"minecraft:ghast":3,"minecraft:blaze":4,"minecraft:cow":6,"minecraft:zombie_pigman":10,"minecraft:horse":9,"minecraft:husk":4,"minecraft:squid":4,"minecraft:wither_skeleton":2,"minecraft:enderman":1},"minecraft:crafted":{"minecraft:oak_planks":700,"minecraft:dark_oak_pressure_plate":2,"minecraft:cooked_chicken":33,"minecraft:stone":33,"minecraft:lever":2,"minecraft:bookshelf":67,"minecraft:cooked_mutton":27,"minecraft:dark_oak_door":12,"minecraft:glass":17,"minecraft:bow":1,"minecraft:iron_boots":1,"minecraft:white_glazed_terracotta":1,"minecraft:chest":20,"minecraft:acacia_fence":174,"minecraft:iron_door":3,"minecraft:rail":48,"minecraft:dried_kelp_block":36,"minecraft:black_wool":3,"minecraft:stone_hoe":2,"minecraft:oak_fence":144,"minecraft:golden_boots":1,"minecraft:glass_bottle":54,"minecraft:oak_slab":6,"minecraft:cooked_porkchop":47,"minecraft:crafting_table":12,"minecraft:wooden_pickaxe":2,"minecraft:rose_red":18,"minecraft:brewing_stand":2,"minecraft:birch_planks":12,"minecraft:dark_oak_slab":6,"minecraft:iron_chestplate":1,"minecraft:golden_leggings":1,"minecraft:charcoal":7,"minecraft:shield":1,"minecraft:stick":492,"minecraft:iron_ingot":70,"minecraft:iron_pickaxe":1,"minecraft:iron_block":1,"minecraft:stone_sword":1,"minecraft:black_bed":1,"minecraft:acacia_door":3,"minecraft:gold_ingot":49,"minecraft:redstone_torch":15,"minecraft:dark_oak_fence_gate":3,"minecraft:stone_shovel":7,"minecraft:iron_nugget":9,"minecraft:acacia_fence_gate":3,"minecraft:furnace":4,"minecraft:stone_button":5,"minecraft:dark_oak_trapdoor":2,"minecraft:bone_meal":9,"minecraft:pink_dye":10,"minecraft:oak_trapdoor":22,"minecraft:dark_oak_fence":30,"minecraft:ladder":3,"minecraft:stone_pickaxe":21,"minecraft:cobblestone_wall":6,"minecraft:dark_oak_planks":1824,"minecraft:lead":4,"minecraft:golden_helmet":1,"minecraft:minecart":2,"minecraft:cooked_beef":13,"minecraft:cooked_cod":1,"minecraft:dark_oak_stairs":20,"minecraft:enchanting_table":1,"minecraft:dried_kelp":291,"minecraft:powered_rail":30,"minecraft:iron_sword":1,"minecraft:golden_shovel":1,"minecraft:bucket":3,"minecraft:acacia_stairs":60,"minecraft:sign":9,"minecraft:stone_axe":9,"minecraft:bread":15,"minecraft:air":0,"minecraft:jungle_planks":40,"minecraft:oak_stairs":68,"minecraft:wooden_axe":1,"minecraft:iron_leggings":1,"minecraft:white_bed":2,"minecraft:acacia_planks":656,"minecraft:torch":224},"minecraft:picked_up":{"minecraft:iron_chestplate":4,"minecraft:birch_door":1,"minecraft:wheat":111,"minecraft:lead":56,"minecraft:diamond_sword":1,"minecraft:oak_stairs":13,"minecraft:brown_bed":2,"minecraft:golden_shovel":4,"minecraft:brewing_stand":1,"minecraft:golden_sword":3,"minecraft:string":67,"minecraft:dark_oak_trapdoor":2,"minecraft:iron_leggings":1,"minecraft:beetroot":113,"minecraft:red_sand":105,"minecraft:gold_nugget":13,"minecraft:bucket":1,"minecraft:black_glazed_terracotta":1,"minecraft:acacia_fence_gate":3,"minecraft:rose_bush":6,"minecraft:redstone_torch":35,"minecraft:iron_pickaxe":1,"minecraft:iron_boots":1,"minecraft:furnace":5,"minecraft:dark_oak_door":9,"minecraft:tipped_arrow":1,"minecraft:golden_helmet":3,"minecraft:stick":92,"minecraft:acacia_fence":34,"minecraft:brown_terracotta":247,"minecraft:oak_fence":126,"minecraft:torch":239,"minecraft:acacia_log":379,"minecraft:porkchop":77,"minecraft:dried_kelp":59,"minecraft:diorite":3,"minecraft:rotten_flesh":44,"minecraft:white_terracotta":20,"minecraft:blaze_rod":2,"minecraft:cod":3,"minecraft:cobblestone":984,"minecraft:birch_log":14,"minecraft:feather":41,"minecraft:cooked_beef":4,"minecraft:andesite":10,"minecraft:iron_door":1,"minecraft:water_bucket":1,"minecraft:jungle_log":32,"minecraft:golden_leggings":3,"minecraft:lapis_lazuli":102,"minecraft:dirt":604,"minecraft:name_tag":1,"minecraft:rose_red":36,"minecraft:sign":23,"minecraft:bone":48,"minecraft:acacia_planks":143,"minecraft:bow":2,"minecraft:wheat_seeds":340,"minecraft:powered_rail":46,"minecraft:stone_hoe":4,"minecraft:oak_planks":188,"minecraft:cooked_porkchop":29,"minecraft:poisonous_potato":5,"minecraft:sand":59,"minecraft:ink_sac":18,"minecraft:acacia_stairs":6,"minecraft:dark_oak_log":1051,"minecraft:red_terracotta":16,"minecraft:stripped_acacia_log":1,"minecraft:light_gray_terracotta":32,"minecraft:diamond":1,"minecraft:lever":1,"minecraft:granite":21,"minecraft:bone_meal":1,"minecraft:emerald":6,"minecraft:bread":6,"minecraft:oak_sapling":64,"minecraft:netherrack":58,"minecraft:dark_oak_fence":22,"minecraft:charcoal":8,"minecraft:coarse_dirt":3,"minecraft:crafting_table":13,"minecraft:ladder":1,"minecraft:chicken":34,"minecraft:nether_wart":31,"minecraft:clay_ball":8,"minecraft:wooden_pickaxe":1,"minecraft:shield":1,"minecraft:oak_trapdoor":1,"minecraft:iron_axe":2,"minecraft:acacia_door":6,"minecraft:item_frame":2,"minecraft:detector_rail":4,"minecraft:beef":13,"minecraft:jungle_sapling":2,"minecraft:iron_nugget":11,"minecraft:poppy":17,"minecraft:light_gray_wool":5,"minecraft:minecart":33,"minecraft:sugar_cane":4,"minecraft:chest":15,"minecraft:birch_sapling":9,"minecraft:egg":316,"minecraft:dark_oak_sapling":133,"minecraft:black_stained_glass":53,"minecraft:stone":1,"minecraft:oak_door":3,"minecraft:brown_glazed_terracotta":1,"minecraft:stone_button":9,"minecraft:carrot":245,"minecraft:redstone":55,"minecraft:dark_oak_planks":328,"minecraft:arrow":25,"minecraft:stone_shovel":5,"minecraft:beetroot_seeds":225,"minecraft:peony":5,"minecraft:nether_bricks":4,"minecraft:pink_glazed_terracotta":1,"minecraft:shears":1,"minecraft:yellow_terracotta":425,"minecraft:saddle":2,"minecraft:gold_ingot":28,"minecraft:mutton":45,"minecraft:rail":133,"minecraft:white_wool":17,"minecraft:clock":1,"minecraft:leather":18,"minecraft:red_glazed_terracotta":1,"minecraft:filled_map":8,"minecraft:birch_planks":10,"minecraft:oak_log":182,"minecraft:golden_boots":2,"minecraft:cobblestone_wall":4,"minecraft:gunpowder":5,"minecraft:paper":29,"minecraft:orange_terracotta":766,"minecraft:cooked_mutton":2,"minecraft:apple":21,"minecraft:kelp":378,"minecraft:iron_ingot":24,"minecraft:stone_pickaxe":7,"minecraft:iron_ore":64,"minecraft:iron_sword":6,"minecraft:acacia_sapling":127,"minecraft:dark_oak_stairs":12,"minecraft:book":9,"minecraft:oak_slab":1,"minecraft:dark_oak_slab":17,"minecraft:pumpkin":6,"minecraft:green_glazed_terracotta":1,"minecraft:quartz":19,"minecraft:dandelion":2,"minecraft:lava_bucket":4,"minecraft:white_bed":5,"minecraft:gold_ore":53,"minecraft:dark_oak_fence_gate":4,"minecraft:spider_eye":6,"minecraft:leather_helmet":2,"minecraft:infested_stone_bricks":1,"minecraft:pumpkin_seeds":7,"minecraft:stone_axe":7,"minecraft:painting":5,"minecraft:terracotta":1111,"minecraft:coal":358,"minecraft:pink_dye":20},"minecraft:killed_by":{"minecraft:spider":1},"minecraft:used":{"minecraft:beetroot":6,"minecraft:red_sand":12,"minecraft:ladder":45,"minecraft:chest":48,"minecraft:white_terracotta":160,"minecraft:iron_sword":415,"minecraft:stone":12,"minecraft:farmland":2,"minecraft:orange_glazed_terracotta":4,"minecraft:nether_bricks":3,"minecraft:carrot":85,"minecraft:acacia_sapling":52,"minecraft:jungle_sapling":4,"minecraft:glass":20,"minecraft:lava_bucket":12,"minecraft:dark_oak_slab":23,"minecraft:stone_brick_stairs":65,"minecraft:stone_bricks":1793,"minecraft:item_frame":5,"minecraft:golden_sword":20,"minecraft:bow":32,"minecraft:written_book":1,"minecraft:oak_sapling":46,"minecraft:furnace":10,"minecraft:beetroot_seeds":53,"minecraft:acacia_fence":526,"minecraft:egg":327,"minecraft:dark_oak_sapling":140,"minecraft:diorite":1,"minecraft:dark_oak_stairs":32,"minecraft:stone_pickaxe":2534,"minecraft:powered_rail":73,"minecraft:oak_planks":146,"minecraft:wooden_pickaxe":20,"minecraft:black_glazed_terracotta":6,"minecraft:dark_oak_trapdoor":2,"minecraft:yellow_terracotta":651,"minecraft:light_gray_terracotta":32,"minecraft:black_bed":1,"minecraft:pumpkin_seeds":14,"minecraft:birch_fence":22,"minecraft:redstone_torch":113,"minecraft:black_terracotta":36,"minecraft:lever":3,"minecraft:acacia_door":3,"minecraft:stone_button":12,"minecraft:dark_oak_log":220,"minecraft:string":2,"minecraft:bread":12,"minecraft:sign":18,"minecraft:white_glazed_terracotta":394,"minecraft:red_terracotta":24,"minecraft:iron_door":2,"minecraft:diamond_sword":46,"minecraft:dark_oak_fence":49,"minecraft:coarse_dirt":2,"minecraft:bone_meal":8,"minecraft:oak_fence":239,"minecraft:oak_trapdoor":15,"minecraft:iron_bars":9,"minecraft:enchanting_table":1,"minecraft:stone_sword":158,"minecraft:acacia_log":21,"minecraft:flint_and_steel":96,"minecraft:stone_shovel":217,"minecraft:redstone":22,"minecraft:dried_kelp":8,"minecraft:stone_hoe":37,"minecraft:cooked_chicken":2,"minecraft:netherrack":4,"minecraft:torch":772,"minecraft:brewing_stand":4,"minecraft:dirt":442,"minecraft:cobblestone_wall":69,"minecraft:granite":1,"minecraft:light_blue_stained_glass":502,"minecraft:spruce_fence":12,"minecraft:birch_door":3,"minecraft:brown_terracotta":507,"minecraft:dark_oak_planks":1055,"minecraft:wooden_axe":59,"minecraft:sea_lantern":31,"minecraft:bookshelf":66,"minecraft:oak_stairs":32,"minecraft:black_stained_glass":38,"minecraft:dark_oak_pressure_plate":2,"minecraft:minecart":27,"minecraft:cooked_beef":1,"minecraft:acacia_planks":227,"minecraft:orange_terracotta":355,"minecraft:brown_bed":6,"minecraft:wheat_seeds":61,"minecraft:cooked_mutton":22,"minecraft:water_bucket":1998,"minecraft:acacia_boat":6,"minecraft:pink_glazed_terracotta":57,"minecraft:glass_bottle":1,"minecraft:blue_wool":1,"minecraft:rail":152,"minecraft:terracotta":1797,"minecraft:tnt":285,"minecraft:crafting_table":26,"minecraft:oak_slab":2,"minecraft:dark_oak_fence_gate":7,"minecraft:painting":5,"minecraft:white_bed":7,"minecraft:infested_stone_bricks":109,"minecraft:brown_glazed_terracotta":7,"minecraft:cyan_stained_glass":1,"minecraft:dark_oak_door":13,"minecraft:oak_log":10,"minecraft:acacia_stairs":52,"minecraft:apple":1,"minecraft:chicken":1,"minecraft:iron_pickaxe":826,"minecraft:detector_rail":4,"minecraft:acacia_fence_gate":7,"minecraft:stone_axe":1242,"minecraft:cobblestone":924,"minecraft:cooked_porkchop":34,"minecraft:bucket":228,"minecraft:glass_pane":2}},"DataVersion":1631}